pyarcS/QueryManager.py
pyarcS/__init__.py
pyarcS-0.2.dist-info/LICENSE
pyarcS-0.2.dist-info/METADATA
pyarcS-0.2.dist-info/WHEEL
pyarcS-0.2.dist-info/top_level.txt
pyarcS-0.2.dist-info/RECORD
