Metadata-Version: 2.1
Name: pyarcS
Version: 0.2
Summary: QueryManager
Home-page: https://github.com/Srinadhch07/QueryManager.git
Author: srinadhch07
Author-email: <srinadhc07@gmail.com>
License: MIT
Keywords: python,query,mysql,update
Classifier: Development Status :: 1 - Planning
Classifier: Intended Audience :: Developers
Classifier: Programming Language :: Python :: 3
Classifier: Operating System :: Unix
Classifier: Operating System :: MacOS :: MacOS X
Classifier: Operating System :: Microsoft :: Windows
Classifier: Intended Audience :: Developers
Classifier: Topic :: Software Development :: Build Tools
Classifier: License :: OSI Approved :: MIT License
Classifier: Programming Language :: Python :: 3.8
Classifier: Programming Language :: Python :: 3.9
Classifier: Programming Language :: Python :: 3.10
License-File: LICENSE
Requires-Dist: mysql-connector-python
